top-with-enable/fixSinkList.v
`timescale 1ns/1ps
`define WORD_WIDTH 16

module fixSinkList(clock, nrst, en, start, address, wr_en, data_in, data_out, done);
	input clock, nrst, en, start;
	input [`WORD_WIDTH-1:0] data_in;
	output done, wr_en;
	output [10:0] address;
	output [`WORD_WIDTH-1:0] data_out;

	// Registers
	reg done_buf, wr_en_buf;
	reg [10:0] address_count;
	reg [`WORD_WIDTH-1:0] data_out_buf, i, j, k;
	reg [`WORD_WIDTH-1:0] knownSinks, sinkIDs, worstHops, qValue, neighborCount, knownSinkCount, sinkIDCount;
	reg [3:0] state;

	always @ (posedge clock) begin
		if (!nrst) begin
			done_buf = 0;
			wr_en_buf = 0;
			address_count = 11'h68A; // neighborCount address
			data_out_buf = 16'h0;			
			state = 12;
			i = 0; // qValue, sinkIDCount
			j = 0; // knownSinks, worstHops
			k = 0; // sinkID_index
		end
		else begin
			case (state)
				0: begin
					if (start) begin
						state = 1;
						address_count = 11'h68A; // neighborCount address
					end
					else state = 0;
				end

				1: begin
					neighborCount = data_in;
					state = 2;
					address_count = 11'h688; // knownSinkCount address
				end

				2: begin
					knownSinkCount = data_in;
					state = 3;
					address_count = 11'h8 + 2*j; // knownSinks address
				end

				3: begin
					knownSinks = data_in;
					state = 4;
					address_count = 11'h68E + 2*i; // sinkIDCount address           
				end

				4: begin                    
					sinkIDCount = data_in;
					state = 5;
					address_count = 11'h248 + 16*i + 2*k; // sinkIDs address
				end

				5: begin
					sinkIDs = data_in;
					// If found, compare with next set of sinkIDs
					if (knownSinks == sinkIDs) begin
						i = i + 1;
						k = 0;

						if (i == neighborCount) begin
							j = j + 1;
							i = 0;
							k = 0;
							
							if (j == knownSinkCount) begin
								state = 11;
							end
							else begin
								state = 3;
								address_count = 11'h8 + 2*j; // knownSinks address
							end
						end
						else begin
							state = 4;
							address_count = 11'h68E + 2*i; // sinkIDCount address
						end
					end
					else begin
						k = k + 1;
						
						if (k == sinkIDCount) begin
							state = 6;  // Append knownSink to sinkIDs
							data_out_buf = knownSinks;
							address_count = 11'h248 + 16*i + 2*k; // sinkIDs address
							wr_en_buf = 1;
							$display("Append knownSink to sinkIDs");
						end
						else begin
							// state = 5;
							address_count = 11'h248 + 16*i + 2*k; // sinkIDs address
						end
					end
				end

				6: begin
					wr_en_buf = 0;
					state = 7;
					address_count = 11'h28 + 2*j; // worstHops address
				end

				7: begin
					worstHops = data_in;
					state = 8;
					address_count = 11'h1C8 + 2*i; // qValue address (read)
				end

				8: begin
					qValue = data_in;
					state = 9;
					data_out_buf = qValue + (worstHops + 1); // Update qValue (add worstHops)
					// address_count = 11'h1C8 + 2*i; // qValue address (write)
					wr_en_buf = 1;
				end

				9: begin
					//wr_en_buf = 0;
					state = 10;
					data_out_buf = sinkIDCount + 1;
					address_count = 11'h68E + 2*i;
					//wr_en_buf = 1;
				end

				10: begin
					wr_en_buf = 0;
					i = i + 1; // Compare knownSink with next set of sinkIDs after append
					k = 0;

					if (i == neighborCount) begin
						j = j + 1;
						i = 0;
						k = 0;
						
						if (j == knownSinkCount) begin
							state = 11;
						end
						else begin
							state = 3;
							address_count = 11'h8 + 2*j; // knownSinks address
						end 
					end
					else begin
						state = 4;
						address_count = 11'h68E + 2*i; // sinkIDCount address
					end 
				end

				11: begin
					done_buf = 1;
					state = 12;
				end

				12: begin
					if (en) begin
						done_buf = 0;
						wr_en_buf = 0;
						address_count = 11'h68A; // neighborCount address
						state = 0;
						i = 0; // qValue, sinkIDCount
						j = 0; // knownSinks, worstHops
						k = 0; // sinkID_index
					end
					else state = 12;
				end

				default: state = 12;
			endcase
		end
	end
	assign done = done_buf;
	assign address = address_count;
	assign wr_en = wr_en_buf;
	assign data_out = data_out_buf;
endmodule

top-with-enable/memory.v
`define MEM_DEPTH  2048
`define MEM_WIDTH  8
`define WORD_WIDTH 16

/* Address List
 * (2/4)        [0x0 - 0x07]        amISink/forAggregation FLAGS (0-3)
 * (2/16)       [0x8 - 0x27]        knownSinks (4-19)
 * (2/16)       [0x28 - 0x47]       worstHops (20-35)
 * (2/64)       [0x48 - 0xC7]       neighborID (36-99)
 * (2/64)       [0xC8 - 0x147]      clusterID (100-163)
 * (2/64)       [0x148 - 0x1C7]     batteryStat (164-227)
 * (2/64)       [0x1C8 - 0x247]     qValue (228-291)
 * (2/8*64)     [0x248 - 0x647]     sinkIDs (292-803)
 * (2/16)       [0x648 - 0x667]     HCM (804-819)
 * (2/16)       [0x668 - 0x687]     betterneighbors (820-835)
 * 
 * (2/1)        [0x688 - 0x689]     knownSinkCount (836)
 * (2/1)        [0x68A - 0x68B]     neighborCount (837)
 * (2/1)        [0x68C - 0x68D]     betterneighborCount (838)
 * (2/64)       [0x68E - 0x70D]     sinkIDCount (839-902)
 */

module mem(clock, address, wr_en, data_in, data_out);
	input clock, wr_en;
	input [10:0] address;
	input [`WORD_WIDTH-1:0] data_in;
	output [`WORD_WIDTH-1:0] data_out;

	//INITIALIZE MEMORY ARRAY
	reg [`MEM_WIDTH-1:0] memory [0:`MEM_DEPTH-1];


	//STORE INITIAL CONTENTS
	//initial begin
	//	$readmemh("./mem.txt", memory);
	//end

	// Test Case
	initial begin
		// FLAGS
		memory['h0] = 0;
		memory['h1] = 0;

		memory['h2] = 0;
		memory['h3] = 0;

		memory['h4] = 0;
		memory['h5] = 0;

		memory['h6] = 0;
		memory['h7] = 0;

		// knownSinks
		memory['h8 + 0] = 0;
		memory['h8 + 1] = 2;

		memory['h8 + 2] = 0;
		memory['h8 + 3] = 5;

		memory['h8 + 4] = 0;
		memory['h8 + 5] = 10;

		memory['h8 + 6] = 0;
		memory['h8 + 7] = 171;

		memory['h8 + 8] = 0;
		memory['h8 + 9] = 205;

		memory['h8 + 10] = 8'b0;
		memory['h8 + 11] = 8'b0;

		// knownSinkCount
		memory['h688] = 0;
		memory['h688 + 1] = 5;
		
		// betterneighbors
		memory['h668 + 0] = 0;
		memory['h668 + 1] = 0;

		memory['h668 + 2] = 0;
		memory['h668 + 3] = 0;

		memory['h668 + 4] = 0;
		memory['h668 + 5] = 0;

		memory['h668 + 6] = 0;
		memory['h668 + 7] = 0;

		memory['h668 + 8] = 0;
		memory['h668 + 9] = 0;
		
		// betterneighborCount
		memory['h68C] = 0;
		memory['h68C + 1] = 0;

		// worstHops
		memory['h28 + 0] = 8'b1;
		memory['h28 + 1] = 8'b01100000;	// 11

		memory['h28 + 2] = 8'b0;
		memory['h28 + 3] = 8'b01100000;	// 3

		memory['h28 + 4] = 8'b0;
		memory['h28 + 5] = 8'b10100000; // 5

		memory['h28 + 6] = 8'b0;
		memory['h28 + 7] = 8'b11100000; // 7

		memory['h28 + 8] = 8'b1;
		memory['h28 + 9] = 8'b10100000; // 13

		// neighborCount
		memory['h68A] = 0;
		memory['h68A + 1] = 4;


		// sinkIDsCount
		memory['h68E + 0] = 0;
		memory['h68E + 1] = 3;

		memory['h68E + 2] = 0;
		memory['h68E + 3] = 5;

		memory['h68E + 4] = 0;
		memory['h68E + 5] = 3;

		memory['h68E + 6] = 0;
		memory['h68E + 7] = 1;

		// sinkIDs
		memory['h248 + 0 + 0] = 0;
		memory['h248 + 0 + 1] = 10;

		memory['h248 + 0 + 2] = 0;
		memory['h248 + 0 + 3] = 171;

		memory['h248 + 0 + 4] = 0;
		memory['h248 + 0 + 5] = 205;

		memory['h248 + 0 + 6] = 0;
		memory['h248 + 0 + 7] = 0;

		memory['h248 + 0 + 8] = 0;
		memory['h248 + 0 + 9] = 0;


		memory['h248 + 16 + 0] = 0;
		memory['h248 + 16 + 1] = 2;

		memory['h248 + 16 + 2] = 0;
		memory['h248 + 16 + 3] = 5;

		memory['h248 + 16 + 4] = 0;
		memory['h248 + 16 + 5] = 10;

		memory['h248 + 16 + 6] = 0;
		memory['h248 + 16 + 7] = 171;

		memory['h248 + 16 + 8] = 0;
		memory['h248 + 16 + 9] = 205;


		memory['h248 + 32 + 0] = 0;
		memory['h248 + 32 + 1] = 2;

		memory['h248 + 32 + 2] = 0;
		memory['h248 + 32 + 3] = 5;

		memory['h248 + 32 + 4] = 0;
		memory['h248 + 32 + 5] = 10;

		memory['h248 + 32 + 6] = 0;
		memory['h248 + 32 + 7] = 0;

		memory['h248 + 32 + 8] = 0;
		memory['h248 + 32 + 9] = 0;


		memory['h248 + 48 + 0] = 0;
		memory['h248 + 48 + 1] = 2;

		memory['h248 + 48 + 2] = 0;
		memory['h248 + 48 + 3] = 0;

		memory['h248 + 48 + 4] = 0;
		memory['h248 + 48 + 5] = 0;

		memory['h248 + 48 + 6] = 0;
		memory['h248 + 48 + 7] = 0;

		memory['h248 + 48 + 8] = 0;
		memory['h248 + 48 + 9] = 0;

		// HCM		
		memory['h648 + 0] = 8'b10110000;	// 5.5
		memory['h648 + 1] = 8'b0;

		memory['h648 + 2] = 8'b10010100;	// 4.64 ~ 4.639892578125
		memory['h648 + 3] = 8'b01111010;

		memory['h648 + 4] = 8'b01111101;	// 3.91 ~ 3.909912109375
		memory['h648 + 5] = 8'b00011110;

		memory['h648 + 6] = 8'b01101001;	// 3.3 ~ 3.2999267578125
		memory['h648 + 7] = 8'b10011001;

		memory['h648 + 8] = 8'b01011000;	// 2.78 ~ 2.7799072265625
		memory['h648 + 9] = 8'b11110101;

		memory['h648 + 10] = 8'b01001011;	// 2.35 ~ 2.3499755859375
		memory['h648 + 11] = 8'b00110011;

		memory['h648 + 12] = 8'b00111111;	// 1.98 ~ 1.97998046875
		memory['h648 + 13] = 8'b01011100;

		memory['h648 + 14] = 8'b00110101;	// 1.67 ~ 1.669921875
		memory['h648 + 15] = 8'b01110000;

		memory['h648 + 16] = 8'b00101101;	// 1.41 ~ 1.409912109375
		memory['h648 + 17] = 8'b00011110;

		memory['h648 + 18] = 8'b00100110;	// 1.19	~ 1.18994140625
		memory['h648 + 19] = 8'b00010100;

		memory['h648 + 20] = 8'b00100000;	// 1.0
		memory['h648 + 21] = 8'b0;


		/* betterNeighborsInMyCluster
		// neighborID
		memory['h48 + 0] = 0;
		memory['h48 + 1] = 1;

		memory['h48 + 2] = 0;
		memory['h48 + 3] = 3;

		memory['h48 + 4] = 0;
		memory['h48 + 5] = 4;

		memory['h48 + 6] = 0;
		memory['h48 + 7] = 6;

		memory['h48 + 8] = 8'b0;
		memory['h48 + 9] = 8'b0;
		
		// clusterID
		memory['hC8 + 0] = 0;
		memory['hC8 + 1] = 9;

		memory['hC8 + 2] = 0;
		memory['hC8 + 3] = 1;

		memory['hC8 + 4] = 0;
		memory['hC8 + 5] = 1;

		memory['hC8 + 6] = 0;
		memory['hC8 + 7] = 3;

		memory['hC8 + 8] = 8'b0;
		memory['hC8 + 9] = 8'b0;

		// qValue
		memory['h1C8 + 0] = 8'b111;			// 60 /1
		memory['h1C8 + 1] = 8'b10000000;
		
		memory['h1C8 + 2] = 8'b101;			// 40 /3
		memory['h1C8 + 3] = 8'b0;

		memory['h1C8 + 4] = 8'b100;			// 35 /4
		memory['h1C8 + 5] = 8'b01100000;
		
		memory['h1C8 + 6] = 8'b1;			// 10 /6
		memory['h1C8 + 7] = 8'b01000000;

		memory['h1C8 + 8] = 8'b0;
		memory['h1C8 + 9] = 8'b0;
		
		// batteryStat
		memory['h148 + 0] = 8'b01000000;	// 0.5
		memory['h148 + 1] = 8'b00000000;

		memory['h148 + 2] = 8'b00000001;	// 0.008
		memory['h148 + 3] = 8'b00000110;

		memory['h148 + 4] = 8'b01011001;	// 0.7
		memory['h148 + 5] = 8'b10011001;

		memory['h148 + 6] = 8'b10000000;	// 1.0
		memory['h148 + 7] = 8'b00000000;
		//*/

		//* fixSinkList, findMyBest testcase

		// neighborID
		memory['h48 + 0] = 0;
		memory['h48 + 1] = 1;

		memory['h48 + 2] = 0;
		memory['h48 + 3] = 3;

		memory['h48 + 4] = 0;
		memory['h48 + 5] = 4;

		memory['h48 + 6] = 0;
		memory['h48 + 7] = 6;
		
		memory['h48 + 8] = 8'b0;
		memory['h48 + 9] = 8'b0;

		// clusterID
		memory['hC8 + 0] = 0;
		memory['hC8 + 1] = 9;

		memory['hC8 + 2] = 0;
		memory['hC8 + 3] = 1;

		memory['hC8 + 4] = 0;
		memory['hC8 + 5] = 1;

		memory['hC8 + 6] = 0;
		memory['hC8 + 7] = 3;

		memory['hC8 + 8] = 8'b0;
		memory['hC8 + 9] = 8'b0;

		// qValue
		memory['h1C8 + 0] = 8'b1;
		memory['h1C8 + 1] = 8'b01000000;

		memory['h1C8 + 2] = 8'b100;
		memory['h1C8 + 3] = 8'b01100000;

		memory['h1C8 + 4] = 8'b101;
		memory['h1C8 + 5] = 8'b0;

		memory['h1C8 + 6] = 8'b111;
		memory['h1C8 + 7] = 8'b10000000;

		memory['h1C8 + 8] = 8'b0;
		memory['h1C8 + 9] = 8'b0;

		//*/


		/* neighborSinkInOtherCluster testcase
		// neighborID
		memory['h48 + 0] = 0;
		memory['h48 + 1] = 3;
		memory['h48 + 2] = 0;
		memory['h48 + 3] = 1;
		memory['h48 + 4] = 0;
		memory['h48 + 5] = 10;
		memory['h48 + 6] = 0;
		memory['h48 + 7] = 6;		
		// clusterID
		memory['hC8 + 0] = 0;
		memory['hC8 + 1] = 1;
		memory['hC8 + 2] = 0;
		memory['hC8 + 3] = 1;
		memory['hC8 + 4] = 0;
		memory['hC8 + 5] = 2;
		memory['hC8 + 6] = 0;
		memory['hC8 + 7] = 3;
		//*/

	end

	//READ PORT
	reg [`WORD_WIDTH-1:0] data_out_buf;

	always@(*)
		data_out_buf <= {memory[address], memory[address+1]};

	assign data_out = data_out_buf;

	//WRITE PORT
	always@(posedge clock) begin
		if (wr_en) begin
			memory[address] <= data_in[15:8];
			memory[address+1] <= data_in[7:0];
		end
	end
endmodule

top-with-enable/tb_fixSinkList.v
`timescale 1ns/1ps
`define WORD_WIDTH 16

/* Address List
 * (2/4)        [0x0 - 0x07]        amISink/forAggregation FLAGS
 * (2/16)       [0x8 - 0x27]        knownSinks  
 * (2/16)       [0x28 - 0x47]       worstHops
 * (2/64)       [0x48 - 0xC7]       neighborID
 * (2/64)       [0xC8 - 0x147]      clusterID
 * (2/64)       [0x148 - 0x1C7]     batteryStat
 * (2/64)       [0x1C8 - 0x247]     qValue
 * (2/8*64)     [0x248 - 0x647]     sinkIDs
 * (2/16)       [0x648 - 0x667]     HCM
 * (2/16)       [0x668 - 0x687]     betterneighbors
 * 
 * (2/1)        [0x688 - 0x689]     knownSinkCount
 * (2/1)        [0x68A - 0x68B]     neighborCount
 * (2/1)        [0x68C - 0x68D]     betterneighborCount
 * (2/64)       [0x68E - 0x70D]     sinkIDCount
 */

`include "memory.v"
`include "fixSinkList.v"

module tb_fixSinkList();
	reg clock, nrst;
	wire wr_en;

	// MEMORY MODULE
	wire [`WORD_WIDTH-1:0] mem_data_in, mem_data_out; 
	wire [10:0] address;
	mem mem1(clock, address, wr_en, mem_data_in, mem_data_out);
	
	reg done_iamDestination, en;
	wire done_fixSinkList;
	fixSinkList fsl1(clock, nrst, en, done_iamDestination, address, wr_en, mem_data_out, mem_data_in, done_fixSinkList);

	// Clock
	initial begin
		clock = 0;
		forever #10 clock = ~clock;
	end

	// Reset
	initial begin
		en = 0;
		nrst = 1;
		#5 nrst = ~nrst;
		#25 nrst = ~nrst;
		#20 en = 1;
		#20 en = 0;
	end

	initial begin
		done_iamDestination = 1;
	end

	initial begin
		$dumpfile("tb_fixSinkList.vcd");
		$dumpvars(0, tb_fixSinkList);

		#5000
		$finish;
	end
endmodule

top-with-enable/tb_fixSinkList.vcd
$date
	Tue Mar 13 20:55:56 2018
$end
$version
	Icarus Verilog
$end
$timescale
	1ps
$end
$scope module tb_fixSinkList $end
$var wire 1 ! wr_en $end
$var wire 16 " mem_data_out [15:0] $end
$var wire 16 # mem_data_in [15:0] $end
$var wire 1 $ done_fixSinkList $end
$var wire 11 % address [10:0] $end
$var reg 1 & clock $end
$var reg 1 ' done_iamDestination $end
$var reg 1 ( en $end
$var reg 1 ) nrst $end
$scope module fsl1 $end
$var wire 11 * address [10:0] $end
$var wire 1 & clock $end
$var wire 16 + data_out [15:0] $end
$var wire 1 $ done $end
$var wire 1 ( en $end
$var wire 1 ) nrst $end
$var wire 1 ' start $end
$var wire 1 ! wr_en $end
$var wire 16 , data_in [15:0] $end
$var reg 11 - address_count [10:0] $end
$var reg 16 . data_out_buf [15:0] $end
$var reg 1 / done_buf $end
$var reg 16 0 i [15:0] $end
$var reg 16 1 j [15:0] $end
$var reg 16 2 k [15:0] $end
$var reg 16 3 knownSinkCount [15:0] $end
$var reg 16 4 knownSinks [15:0] $end
$var reg 16 5 neighborCount [15:0] $end
$var reg 16 6 qValue [15:0] $end
$var reg 16 7 sinkIDCount [15:0] $end
$var reg 16 8 sinkIDs [15:0] $end
$var reg 4 9 state [3:0] $end
$var reg 16 : worstHops [15:0] $end
$var reg 1 ; wr_en_buf $end
$upscope $end
$scope module mem1 $end
$var wire 11 < address [10:0] $end
$var wire 1 & clock $end
$var wire 16 = data_in [15:0] $end
$var wire 16 > data_out [15:0] $end
$var wire 1 ! wr_en $end
$var reg 16 ? data_out_buf [15:0] $end
$upscope $end
$upscope $end
$enddefinitions $end
#0
$dumpvars
bx ?
bx >
bx =
bx <
x;
bx :
bx 9
bx 8
bx 7
bx 6
bx 5
bx 4
bx 3
bx 2
bx 1
bx 0
x/
bx .
bx -
bx ,
bx +
bx *
1)
0(
1'
0&
bx %
x$
bx #
bx "
x!
$end
#5000
0)
#10000
b100 "
b100 ,
b100 >
b100 ?
b11010001010 %
b11010001010 *
b11010001010 <
b11010001010 -
0!
0;
b0 2
b0 1
b0 0
b1100 9
0$
0/
1&
#20000
0&
#30000
1&
1)
#40000
0&
#50000
b0 9
1&
1(
#60000
0&
#70000
b1 9
1&
0(
#80000
0&
#90000
b101 "
b101 ,
b101 >
b101 ?
b11010001000 %
b11010001000 *
b11010001000 <
b11010001000 -
b10 9
b100 5
1&
#100000
0&
#110000
b10 "
b10 ,
b10 >
b10 ?
b1000 %
b1000 *
b1000 <
b1000 -
b11 9
b101 3
1&
#120000
0&
#130000
b11 "
b11 ,
b11 >
b11 ?
b11010001110 %
b11010001110 *
b11010001110 <
b11010001110 -
b100 9
b10 4
1&
#140000
0&
#150000
b1010 "
b1010 ,
b1010 >
b1010 ?
b1001001000 %
b1001001000 *
b1001001000 <
b1001001000 -
b101 9
b11 7
1&
#160000
0&
#170000
b10101011 "
b10101011 ,
b10101011 >
b10101011 ?
b1001001010 %
b1001001010 *
b1001001010 <
b1001001010 -
b1 2
b1010 8
1&
#180000
0&
#190000
b11001101 "
b11001101 ,
b11001101 >
b11001101 ?
b1001001100 %
b1001001100 *
b1001001100 <
b1001001100 -
b10 2
b10101011 8
1&
#200000
0&
#210000
bx "
bx ,
bx >
bx ?
1!
1;
b1001001110 %
b1001001110 *
b1001001110 <
b1001001110 -
b10 #
b10 +
b10 =
b10 .
b110 9
b11 2
b11001101 8
1&
#220000
0&
#230000
b1011 "
b1011 ,
b1011 >
b1011 ?
b101000 %
b101000 *
b101000 <
b101000 -
0!
0;
b111 9
1&
#240000
0&
#250000
b101000000 "
b101000000 ,
b101000000 >
b101000000 ?
b111001000 %
b111001000 *
b111001000 <
b111001000 -
b1000 9
b1011 :
1&
#260000
0&
#270000
1!
1;
b101000000 6
bx #
bx +
bx =
bx .
b1001 9
1&
#280000
0&
#290000
b11 "
b11 ,
b11 >
b11 ?
b11010001110 %
b11010001110 *
b11010001110 <
b11010001110 -
b100 #
b100 +
b100 =
b100 .
b1010 9
1&
#300000
0&
#310000
b101 "
b101 ,
b101 >
b101 ?
b11010010000 %
b11010010000 *
b11010010000 <
b11010010000 -
0!
0;
b100 9
b0 2
b1 0
1&
#320000
0&
#330000
b10 "
b10 ,
b10 >
b10 ?
b1001011000 %
b1001011000 *
b1001011000 <
b1001011000 -
b101 9
b101 7
1&
#340000
0&
#350000
b11 "
b11 ,
b11 >
b11 ?
b11010010010 %
b11010010010 *
b11010010010 <
b11010010010 -
b100 9
b10 0
b10 8
1&
#360000
0&
#370000
b10 "
b10 ,
b10 >
b10 ?
b1001101000 %
b1001101000 *
b1001101000 <
b1001101000 -
b101 9
b11 7
1&
#380000
0&
#390000
b1 "
b1 ,
b1 >
b1 ?
b11010010100 %
b11010010100 *
b11010010100 <
b11010010100 -
b100 9
b11 0
1&
#400000
0&
#410000
b10 "
b10 ,
b10 >
b10 ?
b1001111000 %
b1001111000 *
b1001111000 <
b1001111000 -
b101 9
b1 7
1&
#420000
0&
#430000
b101 "
b101 ,
b101 >
b101 ?
b1010 %
b1010 *
b1010 <
b1010 -
b11 9
b1 1
b0 0
1&
#440000
0&
#450000
b100 "
b100 ,
b100 >
b100 ?
b11010001110 %
b11010001110 *
b11010001110 <
b11010001110 -
b100 9
b101 4
1&
#460000
0&
#470000
b1010 "
b1010 ,
b1010 >
b1010 ?
b1001001000 %
b1001001000 *
b1001001000 <
b1001001000 -
b101 9
b100 7
1&
#480000
0&
#490000
b10101011 "
b10101011 ,
b10101011 >
b10101011 ?
b1001001010 %
b1001001010 *
b1001001010 <
b1001001010 -
b1 2
b1010 8
1&
#500000
0&
#510000
b11001101 "
b11001101 ,
b11001101 >
b11001101 ?
b1001001100 %
b1001001100 *
b1001001100 <
b1001001100 -
b10 2
b10101011 8
1&
#520000
0&
#530000
b10 "
b10 ,
b10 >
b10 ?
b1001001110 %
b1001001110 *
b1001001110 <
b1001001110 -
b11 2
b11001101 8
1&
#540000
0&
#550000
bx "
bx ,
bx >
bx ?
1!
1;
b1001010000 %
b1001010000 *
b1001010000 <
b1001010000 -
b101 #
b101 +
b101 =
b101 .
b110 9
b100 2
b10 8
1&
#560000
0&
#570000
b11 "
b11 ,
b11 >
b11 ?
b101010 %
b101010 *
b101010 <
b101010 -
0!
0;
b111 9
1&
#580000
0&
#590000
b100 "
b100 ,
b100 >
b100 ?
b111001000 %
b111001000 *
b111001000 <
b111001000 -
b1000 9
b11 :
1&
#600000
0&
#610000
1!
1;
b100 6
b101000010 #
b101000010 +
b101000010 =
b101000010 .
b1001 9
1&
#620000
0&
#630000
b11010001110 %
b11010001110 *
b11010001110 <
b11010001110 -
b101 #
b101 +
b101 =
b101 .
b1010 9
1&
#640000
0&
#650000
b101 "
b101 ,
b101 >
b101 ?
b11010010000 %
b11010010000 *
b11010010000 <
b11010010000 -
0!
0;
b100 9
b0 2
b1 0
1&
#660000
0&
#670000
b10 "
b10 ,
b10 >
b10 ?
b1001011000 %
b1001011000 *
b1001011000 <
b1001011000 -
b101 9
b101 7
1&
#680000
0&
#690000
b101 "
b101 ,
b101 >
b101 ?
b1001011010 %
b1001011010 *
b1001011010 <
b1001011010 -
b1 2
1&
#700000
0&
#710000
b11 "
b11 ,
b11 >
b11 ?
b11010010010 %
b11010010010 *
b11010010010 <
b11010010010 -
b100 9
b0 2
b10 0
b101 8
1&
#720000
0&
#730000
b10 "
b10 ,
b10 >
b10 ?
b1001101000 %
b1001101000 *
b1001101000 <
b1001101000 -
b101 9
b11 7
1&
#740000
0&
#750000
b101 "
b101 ,
b101 >
b101 ?
b1001101010 %
b1001101010 *
b1001101010 <
b1001101010 -
b1 2
b10 8
1&
#760000
0&
#770000
b1 "
b1 ,
b1 >
b1 ?
b11010010100 %
b11010010100 *
b11010010100 <
b11010010100 -
b100 9
b0 2
b11 0
b101 8
1&
#780000
0&
#790000
b10 "
b10 ,
b10 >
b10 ?
b1001111000 %
b1001111000 *
b1001111000 <
b1001111000 -
b101 9
b1 7
1&
#800000
0&
#810000
bx "
bx ,
bx >
bx ?
1!
1;
b1001111010 %
b1001111010 *
b1001111010 <
b1001111010 -
b110 9
b1 2
b10 8
1&
#820000
0&
#830000
b11 "
b11 ,
b11 >
b11 ?
b101010 %
b101010 *
b101010 <
b101010 -
0!
0;
b111 9
1&
#840000
0&
#850000
b11110000000 "
b11110000000 ,
b11110000000 >
b11110000000 ?
b111001110 %
b111001110 *
b111001110 <
b111001110 -
b1000 9
1&
#860000
0&
#870000
1!
1;
b11110000000 6
b110 #
b110 +
b110 =
b110 .
b1001 9
1&
#880000
0&
#890000
b1 "
b1 ,
b1 >
b1 ?
b11010010100 %
b11010010100 *
b11010010100 <
b11010010100 -
b10 #
b10 +
b10 =
b10 .
b1010 9
1&
#900000
0&
#910000
b1010 "
b1010 ,
b1010 >
b1010 ?
b1100 %
b1100 *
b1100 <
b1100 -
0!
0;
b11 9
b10 1
b0 2
b0 0
1&
#920000
0&
#930000
b101 "
b101 ,
b101 >
b101 ?
b11010001110 %
b11010001110 *
b11010001110 <
b11010001110 -
b100 9
b1010 4
1&
#940000
0&
#950000
b1010 "
b1010 ,
b1010 >
b1010 ?
b1001001000 %
b1001001000 *
b1001001000 <
b1001001000 -
b101 9
b101 7
1&
#960000
0&
#970000
b101 "
b101 ,
b101 >
b101 ?
b11010010000 %
b11010010000 *
b11010010000 <
b11010010000 -
b100 9
b1 0
b1010 8
1&
#980000
0&
#990000
b10 "
b10 ,
b10 >
b10 ?
b1001011000 %
b1001011000 *
b1001011000 <
b1001011000 -
b101 9
1&
#1000000
0&
#1010000
b101 "
b101 ,
b101 >
b101 ?
b1001011010 %
b1001011010 *
b1001011010 <
b1001011010 -
b1 2
b10 8
1&
#1020000
0&
#1030000
b1010 "
b1010 ,
b1010 >
b1010 ?
b1001011100 %
b1001011100 *
b1001011100 <
b1001011100 -
b10 2
b101 8
1&
#1040000
0&
#1050000
b11 "
b11 ,
b11 >
b11 ?
b11010010010 %
b11010010010 *
b11010010010 <
b11010010010 -
b100 9
b0 2
b10 0
b1010 8
1&
#1060000
0&
#1070000
b10 "
b10 ,
b10 >
b10 ?
b1001101000 %
b1001101000 *
b1001101000 <
b1001101000 -
b101 9
b11 7
1&
#1080000
0&
#1090000
b101 "
b101 ,
b101 >
b101 ?
b1001101010 %
b1001101010 *
b1001101010 <
b1001101010 -
b1 2
b10 8
1&
#1100000
0&
#1110000
b1010 "
b1010 ,
b1010 >
b1010 ?
b1001101100 %
b1001101100 *
b1001101100 <
b1001101100 -
b10 2
b101 8
1&
#1120000
0&
#1130000
b10 "
b10 ,
b10 >
b10 ?
b11010010100 %
b11010010100 *
b11010010100 <
b11010010100 -
b100 9
b0 2
b11 0
b1010 8
1&
#1140000
0&
#1150000
b1001111000 %
b1001111000 *
b1001111000 <
b1001111000 -
b101 9
b10 7
1&
#1160000
0&
#1170000
b101 "
b101 ,
b101 >
b101 ?
b1001111010 %
b1001111010 *
b1001111010 <
b1001111010 -
b1 2
b10 8
1&
#1180000
0&
#1190000
bx "
bx ,
bx >
bx ?
1!
1;
b1001111100 %
b1001111100 *
b1001111100 <
b1001111100 -
b1010 #
b1010 +
b1010 =
b1010 .
b110 9
b10 2
b101 8
1&
#1200000
0&
#1210000
b101 "
b101 ,
b101 >
b101 ?
b101100 %
b101100 *
b101100 <
b101100 -
0!
0;
b111 9
1&
#1220000
0&
#1230000
b10 "
b10 ,
b10 >
b10 ?
b111001110 %
b111001110 *
b111001110 <
b111001110 -
b1000 9
b101 :
1&
#1240000
0&
#1250000
1!
1;
b10 6
b11110000100 #
b11110000100 +
b11110000100 =
b11110000100 .
b1001 9
1&
#1260000
0&
#1270000
b11010010100 %
b11010010100 *
b11010010100 <
b11010010100 -
b11 #
b11 +
b11 =
b11 .
b1010 9
1&
#1280000
0&
#1290000
b10101011 "
b10101011 ,
b10101011 >
b10101011 ?
b1110 %
b1110 *
b1110 <
b1110 -
0!
0;
b11 9
b11 1
b0 2
b0 0
1&
#1300000
0&
#1310000
b101 "
b101 ,
b101 >
b101 ?
b11010001110 %
b11010001110 *
b11010001110 <
b11010001110 -
b100 9
b10101011 4
1&
#1320000
0&
#1330000
b1010 "
b1010 ,
b1010 >
b1010 ?
b1001001000 %
b1001001000 *
b1001001000 <
b1001001000 -
b101 9
b101 7
1&
#1340000
0&
#1350000
b10101011 "
b10101011 ,
b10101011 >
b10101011 ?
b1001001010 %
b1001001010 *
b1001001010 <
b1001001010 -
b1 2
b1010 8
1&
#1360000
0&
#1370000
b101 "
b101 ,
b101 >
b101 ?
b11010010000 %
b11010010000 *
b11010010000 <
b11010010000 -
b100 9
b0 2
b1 0
b10101011 8
1&
#1380000
0&
#1390000
b10 "
b10 ,
b10 >
b10 ?
b1001011000 %
b1001011000 *
b1001011000 <
b1001011000 -
b101 9
1&
#1400000
0&
#1410000
b101 "
b101 ,
b101 >
b101 ?
b1001011010 %
b1001011010 *
b1001011010 <
b1001011010 -
b1 2
b10 8
1&
#1420000
0&
#1430000
b1010 "
b1010 ,
b1010 >
b1010 ?
b1001011100 %
b1001011100 *
b1001011100 <
b1001011100 -
b10 2
b101 8
1&
#1440000
0&
#1450000
b10101011 "
b10101011 ,
b10101011 >
b10101011 ?
b1001011110 %
b1001011110 *
b1001011110 <
b1001011110 -
b11 2
b1010 8
1&
#1460000
0&
#1470000
b11 "
b11 ,
b11 >
b11 ?
b11010010010 %
b11010010010 *
b11010010010 <
b11010010010 -
b100 9
b0 2
b10 0
b10101011 8
1&
#1480000
0&
#1490000
b10 "
b10 ,
b10 >
b10 ?
b1001101000 %
b1001101000 *
b1001101000 <
b1001101000 -
b101 9
b11 7
1&
#1500000
0&
#1510000
b101 "
b101 ,
b101 >
b101 ?
b1001101010 %
b1001101010 *
b1001101010 <
b1001101010 -
b1 2
b10 8
1&
#1520000
0&
#1530000
b1010 "
b1010 ,
b1010 >
b1010 ?
b1001101100 %
b1001101100 *
b1001101100 <
b1001101100 -
b10 2
b101 8
1&
#1540000
0&
